linked_select2/urls.py
linked_select2/forms.py
linked_select2/__init__.py
linked_select2/views.py
linked_select2/migrations/__init__.py
linked_select2/static/django_select2/django_select2.js
example/__init__.py
example/limit_queryset/widgets.py
example/limit_queryset/forms.py
example/limit_queryset/__init__.py
example/limit_queryset/admin.py
example/limit_queryset/models.py
Django_Linked_Select2-0.7.1.dist-info/METADATA
Django_Linked_Select2-0.7.1.dist-info/WHEEL
Django_Linked_Select2-0.7.1.dist-info/RECORD
Django_Linked_Select2-0.7.1.dist-info/DESCRIPTION.rst
Django_Linked_Select2-0.7.1.dist-info/metadata.json
Django_Linked_Select2-0.7.1.dist-info/top_level.txt
