Metadata-Version: 2.0
Name: Django-Linked-Select2
Version: 0.7.1
Summary: Django-Select2 extended with dependant widgets
Home-page: https://bitbucket.org/merixstudio/django-linked-select2
Author: Miron Olszewski
Author-email: mionolski@gmail.com
License: LICENSE.txt
Platform: UNKNOWN
Classifier: Environment :: Web Environment
Classifier: Framework :: Django
Classifier: Framework :: Django :: 1.9
Classifier: Intended Audience :: Developers
Classifier: License :: OSI Approved :: Apache Software License
Classifier: Operating System :: OS Independent
Classifier: Programming Language :: Python
Classifier: Programming Language :: Python :: 2
Classifier: Programming Language :: Python :: 3
Classifier: Topic :: Internet :: WWW/HTTP
Classifier: Topic :: Internet :: WWW/HTTP :: Dynamic Content
Requires-Dist: Django-Select2 (>=5.8.6)
